koyaneframework/__init__.py
koyaneframework/cli.py
koyaneframework/core/__init__.py
koyaneframework/core/analyzer/__init__.py
koyaneframework/core/analyzer/analyzer.py
koyaneframework/core/analyzer/analyzer_content.py
koyaneframework/core/analyzer/analyzer_general.py
koyaneframework/core/editor/__init__.py
koyaneframework/core/editor/editor.py
koyaneframework/core/generator/__init__.py
koyaneframework/core/generator/maskChar.py
koyaneframework/core/generator/mask_interpreter.py
koyaneframework/core/generator/wordlist_generator.py
koyaneframework/core/utils/__init__.py
koyaneframework/core/utils/utils.py
koyaneframework/core/utils/word_sources.py
koyaneframework/enums/Categories.py
koyaneframework/enums/__init__.py
koyaneframework/enums/keys.py
koyaneframework/load_animation.py
koyaneframework/output/__init__.py
koyaneframework/output/banner.py
koyaneframework/output/help_cli_texts.py
koyaneframework/output/output_printer.py
koyaneframework-0.0.2.dist-info/LICENSE
koyaneframework-0.0.2.dist-info/METADATA
koyaneframework-0.0.2.dist-info/WHEEL
koyaneframework-0.0.2.dist-info/entry_points.txt
koyaneframework-0.0.2.dist-info/RECORD
