Metadata-Version: 2.1
Name: koyaneframework
Version: 0.0.2
Summary: wordlist forge & analysis toolkit
Author: Puppetm4ster
Requires-Python: >=3.11,<4.0
Classifier: Programming Language :: Python :: 3
Classifier: Programming Language :: Python :: 3.11
Classifier: Programming Language :: Python :: 3.12
Requires-Dist: chardet (>=5.2.0,<6.0.0)
Requires-Dist: poetry-core (>=2.1.3,<3.0.0)
Requires-Dist: pyfiglet (>=1.0.3,<2.0.0)
Requires-Dist: typer (>=0.16.0,<0.17.0)
